tumblr_scraper/__init__.py
tumblr_scraper/__version__.py
tumblr_scraper/blogs.py
tumblr_scraper/constants.py
tumblr_scraper/download.py
tumblr_scraper/http.py
tumblr_scraper/main.py
tumblr_scraper/pages.py
tumblr_scraper/utils.py
tumblr_scraper-0.1.0.dist-info/LICENSE
tumblr_scraper-0.1.0.dist-info/METADATA
tumblr_scraper-0.1.0.dist-info/WHEEL
tumblr_scraper-0.1.0.dist-info/entry_points.txt
tumblr_scraper-0.1.0.dist-info/top_level.txt
tumblr_scraper-0.1.0.dist-info/RECORD
