Metadata-Version: 2.1
Name: tumblr-scraper
Version: 0.1.0
Summary: A command-line scraper written in Python for tumblr.
Home-page: https://github.com/giosali/tumblr-scraper
Author: Giovanni Salinas
Author-email: gbs3@protonmail.com
License: MIT
Project-URL: Source, https://github.com/giosali/tumblr-scraper
Keywords: tumblr,scraper,download,images,videos
Platform: UNKNOWN
Classifier: Development Status :: 4 - Beta
Classifier: Programming Language :: Python :: 3.7
Classifier: Programming Language :: Python :: 3.8
Classifier: Programming Language :: Python :: 3.9
Classifier: Operating System :: OS Independent
Requires-Python: >=3.7
Requires-Dist: beautifulsoup4 (>=4.10.0)
Requires-Dist: httpx[http2] (>=0.19.0)
Requires-Dist: tqdm (>=4.62.2)
